denmarf/__init__.py
denmarf/density.py
denmarf/flows.py
denmarf/transform.py
denmarf/utils.py
denmarf-0.3.2.dist-info/LICENSE
denmarf-0.3.2.dist-info/METADATA
denmarf-0.3.2.dist-info/WHEEL
denmarf-0.3.2.dist-info/top_level.txt
denmarf-0.3.2.dist-info/RECORD
